flaxkv/__init__.py
flaxkv/__main__.py
flaxkv/_sqlite.py
flaxkv/core.py
flaxkv/decorators.py
flaxkv/exceptions.py
flaxkv/helper.py
flaxkv/log.py
flaxkv/manager.py
flaxkv/pack.py
flaxkv/serve/__init__.py
flaxkv/serve/app.py
flaxkv/serve/interface.py
flaxkv/serve/manager.py
flaxkv/serve/pub_sub.py
flaxkv/serve/route.py
flaxkv-0.2.9.dist-info/METADATA
flaxkv-0.2.9.dist-info/WHEEL
flaxkv-0.2.9.dist-info/entry_points.txt
flaxkv-0.2.9.dist-info/licenses/LICENSE
flaxkv-0.2.9.dist-info/RECORD
