Metadata-Version: 2.3
Name: flaxkv
Version: 0.2.9
Summary: A high-performance dictionary database.
Project-URL: Homepage, https://github.com/KenyonY/flaxkv
Project-URL: Documentation, https://github.com/KenyonY/flaxkv#flaxkv
Project-URL: Issues, https://github.com/KenyonY/flaxkv/issues
Project-URL: Source, https://github.com/KenyonY/flaxkv
Author-email: "K.Y" <beidongjiedeguang@gmail.com>
License-File: LICENSE
Keywords: Machine Learning,NLP,leveldb,lmdb,on-disk dict,persistent-storage
Classifier: Development Status :: 5 - Production/Stable
Classifier: Operating System :: OS Independent
Classifier: Programming Language :: Python :: 3
Requires-Python: >=3.8
Requires-Dist: fire
Requires-Dist: lmdb>=1.4.1
Requires-Dist: loguru>=0.7.0
Requires-Dist: msgpack
Requires-Dist: msgspec>=0.18.4
Requires-Dist: numpy
Requires-Dist: orjson>=3.9
Requires-Dist: plyvel-ci>=1.5.0; sys_platform == 'darwin'
Requires-Dist: plyvel-ci>=1.5.0; sys_platform == 'win32'
Requires-Dist: plyvel>=1.5.0; sys_platform == 'linux'
Requires-Dist: psutil
Requires-Dist: pytz
Requires-Dist: rich
Requires-Dist: typing-extensions>=4.7.1; python_version < '3.11'
Provides-Extra: client
Requires-Dist: httpx[http2]; extra == 'client'
Provides-Extra: server
Requires-Dist: httpx[http2]; extra == 'server'
Requires-Dist: hypercorn; extra == 'server'
Requires-Dist: litestar>=2.5.0; extra == 'server'
Requires-Dist: uvicorn; extra == 'server'
Requires-Dist: uvloop; (sys_platform == 'linux') and extra == 'server'
Provides-Extra: test
Requires-Dist: httpx[http2]; extra == 'test'
Requires-Dist: hypercorn; extra == 'test'
Requires-Dist: litestar>=2.5.0; extra == 'test'
Requires-Dist: pandas; extra == 'test'
Requires-Dist: pytest; extra == 'test'
Requires-Dist: pytest-aiohttp; extra == 'test'
Requires-Dist: sparrow-python; extra == 'test'
Requires-Dist: uvicorn; extra == 'test'
Requires-Dist: uvloop; (sys_platform == 'linux') and extra == 'test'
